{
  "nodes":[
    {"name":"Myriel","type":1},
    {"name":"Napoleon","type":1},
    {"name":"Mlle.Baptistine","type":1},
    {"name":"Mme.Magloire","type":1},
    {"name":"CountessdeLo","type":1},
    {"name":"Geborand","type":1},
    {"name":"Champtercier","type":1},
    {"name":"Cravatte","type":1},
    {"name":"Count","type":1},
    {"name":"OldMan","type":1},
    {"name":"Labarre","type":2},
    {"name":"Valjean","type":2},
    {"name":"Marguerite","type":3},
    {"name":"Mme.deR","type":2},
    {"name":"Isabeau","type":2},
    {"name":"Gervais","type":2},
    {"name":"Tholomyes","type":3},
    {"name":"Listolier","type":3},
    {"name":"Fameuil","type":3},
    {"name":"Blacheville","type":3},
    {"name":"Favourite","type":3},
    {"name":"Dahlia","type":3},
    {"name":"Zephine","type":3},
    {"name":"Fantine","type":3},
    {"name":"Mme.Thenardier","type":4},
    {"name":"Thenardier","type":4},
    {"name":"Cosette","type":5},
    {"name":"Javert","type":4},
    {"name":"Fauchelevent","type":0},
    {"name":"Bamatabois","type":2},
    {"name":"Perpetue","type":3},
    {"name":"Simplice","type":2},
    {"name":"Scaufflaire","type":2},
    {"name":"Woman1","type":2},
    {"name":"Judge","type":2},
    {"name":"Champmathieu","type":2},
    {"name":"Brevet","type":2},
    {"name":"Chenildieu","type":2},
    {"name":"Cochepaille","type":2},
    {"name":"Pontmercy","type":4},
    {"name":"Boulatruelle","type":6},
    {"name":"Eponine","type":4},
    {"name":"Anzelma","type":4},
    {"name":"Woman2","type":5},
    {"name":"MotherInnocent","type":0},
    {"name":"Gribier","type":0},
    {"name":"Jondrette","type":7},
    {"name":"Mme.Burgon","type":7},
    {"name":"Gavroche","type":8},
    {"name":"Gillenormand","type":5},
    {"name":"Magnon","type":5},
    {"name":"Mlle.Gillenormand","type":5},
    {"name":"Mme.Pontmercy","type":5},
    {"name":"Mlle.Vaubois","type":5},
    {"name":"Lt.Gillenormand","type":5},
    {"name":"Marius","type":8},
    {"name":"BaronessT","type":5},
    {"name":"Mabeuf","type":8},
    {"name":"Enjolras","type":8},
    {"name":"Combeferre","type":8},
    {"name":"Prouvaire","type":8},
    {"name":"Feuilly","type":8},
    {"name":"Courfeyrac","type":8},
    {"name":"Bahorel","type":8},
    {"name":"Bossuet","type":8},
    {"name":"Joly","type":8},
    {"name":"Grantaire","type":8},
    {"name":"MotherPlutarch","type":9},
    {"name":"Gueulemer","type":4},
    {"name":"Babet","type":4},
    {"name":"Claquesous","type":4},
    {"name":"Montparnasse","type":4},
    {"name":"Toussaint","type":5},
    {"name":"Child1","type":10},
    {"name":"Child2","type":10},
    {"name":"Brujon","type":4},
    {"name":"Mme.Hucheloup","type":8}
  ],
  "links":[
    {"source":1,"target":0,"weight":1},
    {"source":2,"target":0,"weight":8},
    {"source":3,"target":0,"weight":10},
    {"source":3,"target":2,"weight":6},
    {"source":4,"target":0,"weight":1},
    {"source":5,"target":0,"weight":1},
    {"source":6,"target":0,"weight":1},
    {"source":7,"target":0,"weight":1},
    {"source":8,"target":0,"weight":2},
    {"source":9,"target":0,"weight":1},
    {"source":11,"target":10,"weight":1},
    {"source":11,"target":3,"weight":3},
    {"source":11,"target":2,"weight":3},
    {"source":11,"target":0,"weight":5},
    {"source":12,"target":11,"weight":1},
    {"source":13,"target":11,"weight":1},
    {"source":14,"target":11,"weight":1},
    {"source":15,"target":11,"weight":1},
    {"source":17,"target":16,"weight":4},
    {"source":18,"target":16,"weight":4},
    {"source":18,"target":17,"weight":4},
    {"source":19,"target":16,"weight":4},
    {"source":19,"target":17,"weight":4},
    {"source":19,"target":18,"weight":4},
    {"source":20,"target":16,"weight":3},
    {"source":20,"target":17,"weight":3},
    {"source":20,"target":18,"weight":3},
    {"source":20,"target":19,"weight":4},
    {"source":21,"target":16,"weight":3},
    {"source":21,"target":17,"weight":3},
    {"source":21,"target":18,"weight":3},
    {"source":21,"target":19,"weight":3},
    {"source":21,"target":20,"weight":5},
    {"source":22,"target":16,"weight":3},
    {"source":22,"target":17,"weight":3},
    {"source":22,"target":18,"weight":3},
    {"source":22,"target":19,"weight":3},
    {"source":22,"target":20,"weight":4},
    {"source":22,"target":21,"weight":4},
    {"source":23,"target":16,"weight":3},
    {"source":23,"target":17,"weight":3},
    {"source":23,"target":18,"weight":3},
    {"source":23,"target":19,"weight":3},
    {"source":23,"target":20,"weight":4},
    {"source":23,"target":21,"weight":4},
    {"source":23,"target":22,"weight":4},
    {"source":23,"target":12,"weight":2},
    {"source":23,"target":11,"weight":9},
    {"source":24,"target":23,"weight":2},
    {"source":24,"target":11,"weight":7},
    {"source":25,"target":24,"weight":13},
    {"source":25,"target":23,"weight":1},
    {"source":25,"target":11,"weight":12},
    {"source":26,"target":24,"weight":4},
    {"source":26,"target":11,"weight":31},
    {"source":26,"target":16,"weight":1},
    {"source":26,"target":25,"weight":1},
    {"source":27,"target":11,"weight":17},
    {"source":27,"target":23,"weight":5},
    {"source":27,"target":25,"weight":5},
    {"source":27,"target":24,"weight":1},
    {"source":27,"target":26,"weight":1},
    {"source":28,"target":11,"weight":8},
    {"source":28,"target":27,"weight":1},
    {"source":29,"target":23,"weight":1},
    {"source":29,"target":27,"weight":1},
    {"source":29,"target":11,"weight":2},
    {"source":30,"target":23,"weight":1},
    {"source":31,"target":30,"weight":2},
    {"source":31,"target":11,"weight":3},
    {"source":31,"target":23,"weight":2},
    {"source":31,"target":27,"weight":1},
    {"source":32,"target":11,"weight":1},
    {"source":33,"target":11,"weight":2},
    {"source":33,"target":27,"weight":1},
    {"source":34,"target":11,"weight":3},
    {"source":34,"target":29,"weight":2},
    {"source":35,"target":11,"weight":3},
    {"source":35,"target":34,"weight":3},
    {"source":35,"target":29,"weight":2},
    {"source":36,"target":34,"weight":2},
    {"source":36,"target":35,"weight":2},
    {"source":36,"target":11,"weight":2},
    {"source":36,"target":29,"weight":1},
    {"source":37,"target":34,"weight":2},
    {"source":37,"target":35,"weight":2},
    {"source":37,"target":36,"weight":2},
    {"source":37,"target":11,"weight":2},
    {"source":37,"target":29,"weight":1},
    {"source":38,"target":34,"weight":2},
    {"source":38,"target":35,"weight":2},
    {"source":38,"target":36,"weight":2},
    {"source":38,"target":37,"weight":2},
    {"source":38,"target":11,"weight":2},
    {"source":38,"target":29,"weight":1},
    {"source":39,"target":25,"weight":1},
    {"source":40,"target":25,"weight":1},
    {"source":41,"target":24,"weight":2},
    {"source":41,"target":25,"weight":3},
    {"source":42,"target":41,"weight":2},
    {"source":42,"target":25,"weight":2},
    {"source":42,"target":24,"weight":1},
    {"source":43,"target":11,"weight":3},
    {"source":43,"target":26,"weight":1},
    {"source":43,"target":27,"weight":1},
    {"source":44,"target":28,"weight":3},
    {"source":44,"target":11,"weight":1},
    {"source":45,"target":28,"weight":2},
    {"source":47,"target":46,"weight":1},
    {"source":48,"target":47,"weight":2},
    {"source":48,"target":25,"weight":1},
    {"source":48,"target":27,"weight":1},
    {"source":48,"target":11,"weight":1},
    {"source":49,"target":26,"weight":3},
    {"source":49,"target":11,"weight":2},
    {"source":50,"target":49,"weight":1},
    {"source":50,"target":24,"weight":1},
    {"source":51,"target":49,"weight":9},
    {"source":51,"target":26,"weight":2},
    {"source":51,"target":11,"weight":2},
    {"source":52,"target":51,"weight":1},
    {"source":52,"target":39,"weight":1},
    {"source":53,"target":51,"weight":1},
    {"source":54,"target":51,"weight":2},
    {"source":54,"target":49,"weight":1},
    {"source":54,"target":26,"weight":1},
    {"source":55,"target":51,"weight":6},
    {"source":55,"target":49,"weight":12},
    {"source":55,"target":39,"weight":1},
    {"source":55,"target":54,"weight":1},
    {"source":55,"target":26,"weight":21},
    {"source":55,"target":11,"weight":19},
    {"source":55,"target":16,"weight":1},
    {"source":55,"target":25,"weight":2},
    {"source":55,"target":41,"weight":5},
    {"source":55,"target":48,"weight":4},
    {"source":56,"target":49,"weight":1},
    {"source":56,"target":55,"weight":1},
    {"source":57,"target":55,"weight":1},
    {"source":57,"target":41,"weight":1},
    {"source":57,"target":48,"weight":1},
    {"source":58,"target":55,"weight":7},
    {"source":58,"target":48,"weight":7},
    {"source":58,"target":27,"weight":6},
    {"source":58,"target":57,"weight":1},
    {"source":58,"target":11,"weight":4},
    {"source":59,"target":58,"weight":15},
    {"source":59,"target":55,"weight":5},
    {"source":59,"target":48,"weight":6},
    {"source":59,"target":57,"weight":2},
    {"source":60,"target":48,"weight":1},
    {"source":60,"target":58,"weight":4},
    {"source":60,"target":59,"weight":2},
    {"source":61,"target":48,"weight":2},
    {"source":61,"target":58,"weight":6},
    {"source":61,"target":60,"weight":2},
    {"source":61,"target":59,"weight":5},
    {"source":61,"target":57,"weight":1},
    {"source":61,"target":55,"weight":1},
    {"source":62,"target":55,"weight":9},
    {"source":62,"target":58,"weight":17},
    {"source":62,"target":59,"weight":13},
    {"source":62,"target":48,"weight":7},
    {"source":62,"target":57,"weight":2},
    {"source":62,"target":41,"weight":1},
    {"source":62,"target":61,"weight":6},
    {"source":62,"target":60,"weight":3},
    {"source":63,"target":59,"weight":5},
    {"source":63,"target":48,"weight":5},
    {"source":63,"target":62,"weight":6},
    {"source":63,"target":57,"weight":2},
    {"source":63,"target":58,"weight":4},
    {"source":63,"target":61,"weight":3},
    {"source":63,"target":60,"weight":2},
    {"source":63,"target":55,"weight":1},
    {"source":64,"target":55,"weight":5},
    {"source":64,"target":62,"weight":12},
    {"source":64,"target":48,"weight":5},
    {"source":64,"target":63,"weight":4},
    {"source":64,"target":58,"weight":10},
    {"source":64,"target":61,"weight":6},
    {"source":64,"target":60,"weight":2},
    {"source":64,"target":59,"weight":9},
    {"source":64,"target":57,"weight":1},
    {"source":64,"target":11,"weight":1},
    {"source":65,"target":63,"weight":5},
    {"source":65,"target":64,"weight":7},
    {"source":65,"target":48,"weight":3},
    {"source":65,"target":62,"weight":5},
    {"source":65,"target":58,"weight":5},
    {"source":65,"target":61,"weight":5},
    {"source":65,"target":60,"weight":2},
    {"source":65,"target":59,"weight":5},
    {"source":65,"target":57,"weight":1},
    {"source":65,"target":55,"weight":2},
    {"source":66,"target":64,"weight":3},
    {"source":66,"target":58,"weight":3},
    {"source":66,"target":59,"weight":1},
    {"source":66,"target":62,"weight":2},
    {"source":66,"target":65,"weight":2},
    {"source":66,"target":48,"weight":1},
    {"source":66,"target":63,"weight":1},
    {"source":66,"target":61,"weight":1},
    {"source":66,"target":60,"weight":1},
    {"source":67,"target":57,"weight":3},
    {"source":68,"target":25,"weight":5},
    {"source":68,"target":11,"weight":1},
    {"source":68,"target":24,"weight":1},
    {"source":68,"target":27,"weight":1},
    {"source":68,"target":48,"weight":1},
    {"source":68,"target":41,"weight":1},
    {"source":69,"target":25,"weight":6},
    {"source":69,"target":68,"weight":6},
    {"source":69,"target":11,"weight":1},
    {"source":69,"target":24,"weight":1},
    {"source":69,"target":27,"weight":2},
    {"source":69,"target":48,"weight":1},
    {"source":69,"target":41,"weight":1},
    {"source":70,"target":25,"weight":4},
    {"source":70,"target":69,"weight":4},
    {"source":70,"target":68,"weight":4},
    {"source":70,"target":11,"weight":1},
    {"source":70,"target":24,"weight":1},
    {"source":70,"target":27,"weight":1},
    {"source":70,"target":41,"weight":1},
    {"source":70,"target":58,"weight":1},
    {"source":71,"target":27,"weight":1},
    {"source":71,"target":69,"weight":2},
    {"source":71,"target":68,"weight":2},
    {"source":71,"target":70,"weight":2},
    {"source":71,"target":11,"weight":1},
    {"source":71,"target":48,"weight":1},
    {"source":71,"target":41,"weight":1},
    {"source":71,"target":25,"weight":1},
    {"source":72,"target":26,"weight":2},
    {"source":72,"target":27,"weight":1},
    {"source":72,"target":11,"weight":1},
    {"source":73,"target":48,"weight":2},
    {"source":74,"target":48,"weight":2},
    {"source":74,"target":73,"weight":3},
    {"source":75,"target":69,"weight":3},
    {"source":75,"target":68,"weight":3},
    {"source":75,"target":25,"weight":3},
    {"source":75,"target":48,"weight":1},
    {"source":75,"target":41,"weight":1},
    {"source":75,"target":70,"weight":1},
    {"source":75,"target":71,"weight":1},
    {"source":76,"target":64,"weight":1},
    {"source":76,"target":65,"weight":1},
    {"source":76,"target":66,"weight":1},
    {"source":76,"target":63,"weight":1},
    {"source":76,"target":62,"weight":1},
    {"source":76,"target":48,"weight":1},
    {"source":76,"target":58,"weight":1}
  ]
}